xia_pusher/__init__.py
xia_pusher/pusher.cp39-win_amd64.pyd
xia_pusher-0.1.6.dist-info/LICENSE.txt
xia_pusher-0.1.6.dist-info/METADATA
xia_pusher-0.1.6.dist-info/WHEEL
xia_pusher-0.1.6.dist-info/top_level.txt
xia_pusher-0.1.6.dist-info/RECORD
